setup.py
binomial_gaussian_distribution_pkg/Binomialdistribution.py
binomial_gaussian_distribution_pkg/Gaussiandistribution.py
binomial_gaussian_distribution_pkg/Generaldistribution.py
binomial_gaussian_distribution_pkg/__init__.py
binomial_gaussian_distribution_pkg.egg-info/PKG-INFO
binomial_gaussian_distribution_pkg.egg-info/SOURCES.txt
binomial_gaussian_distribution_pkg.egg-info/dependency_links.txt
binomial_gaussian_distribution_pkg.egg-info/not-zip-safe
binomial_gaussian_distribution_pkg.egg-info/top_level.txt