Metadata-Version: 1.0
Name: binomial-gaussian-distribution-pkg
Version: 1.0
Summary: Binomial and Gaussian Distribution
Home-page: UNKNOWN
Author: John Tian
Author-email: johntian2014@gmail.com
License: UNKNOWN
Platform: UNKNOWN
